{"cameraMode":{"drawMode":0,"name":"Shaded","section":"Shading Mode"},"sceneLighting":true,"audioPlay":false,"sceneViewState":{"m_AlwaysRefresh":false,"showFog":true,"showSkybox":true,"showFlares":true,"showImageEffects":true,"showParticleSystems":true,"showVisualEffectGraphs":true,"m_FxEnabled":true},"in2DMode":false,"pivot":{"x":-232.0,"y":5.0,"z":-460.0},"rotation":{"x":0.26756027340888979,"y":-0.07938579469919205,"z":0.022123226895928384,"w":0.9600043296813965},"size":12.12435531616211,"orthographic":false}